julia_pkg/Manifest.toml
julia_pkg/Project.toml
mrmustard/README.md
mrmustard/__init__.py
mrmustard/_version.py
mrmustard/lab/__init__.py
mrmustard/lab/abstract/__init__.py
mrmustard/lab/abstract/measurement.py
mrmustard/lab/abstract/state.py
mrmustard/lab/abstract/transformation.py
mrmustard/lab/circuit.py
mrmustard/lab/circuit_drawer.py
mrmustard/lab/detectors.py
mrmustard/lab/gates.py
mrmustard/lab/states.py
mrmustard/lab/utils.py
mrmustard/lab_dev/wires.py
mrmustard/math/__init__.py
mrmustard/math/autocast.py
mrmustard/math/backend_base.py
mrmustard/math/backend_manager.py
mrmustard/math/backend_numpy.py
mrmustard/math/backend_tensorflow.py
mrmustard/math/caching.py
mrmustard/math/lattice/__init__.py
mrmustard/math/lattice/neighbors.py
mrmustard/math/lattice/paths.py
mrmustard/math/lattice/pivots.py
mrmustard/math/lattice/steps.py
mrmustard/math/lattice/strategies/__init__.py
mrmustard/math/lattice/strategies/beamsplitter.py
mrmustard/math/lattice/strategies/binomial.py
mrmustard/math/lattice/strategies/compactFock/__init__.py
mrmustard/math/lattice/strategies/compactFock/diagonal_amps.py
mrmustard/math/lattice/strategies/compactFock/diagonal_grad.py
mrmustard/math/lattice/strategies/compactFock/helperFunctions.py
mrmustard/math/lattice/strategies/compactFock/inputValidation.py
mrmustard/math/lattice/strategies/compactFock/singleLeftoverMode_amps.py
mrmustard/math/lattice/strategies/compactFock/singleLeftoverMode_grad.py
mrmustard/math/lattice/strategies/displacement.py
mrmustard/math/lattice/strategies/flat_indices.py
mrmustard/math/lattice/strategies/julia/compactFock/diagonal_amps.jl
mrmustard/math/lattice/strategies/julia/compactFock/diagonal_grad.jl
mrmustard/math/lattice/strategies/julia/compactFock/helperFunctions.jl
mrmustard/math/lattice/strategies/julia/compactFock/singleLeftoverMode_amps.jl
mrmustard/math/lattice/strategies/julia/compactFock/singleLeftoverMode_grad.jl
mrmustard/math/lattice/strategies/julia/getPrecision.jl
mrmustard-0.7.3.dist-info/LICENSE
mrmustard-0.7.3.dist-info/METADATA
mrmustard-0.7.3.dist-info/WHEEL
mrmustard-0.7.3.dist-info/RECORD
