Metadata-Version: 2.1
Name: mrmustard
Version: 0.7.3
Summary: Differentiable quantum Gaussian circuits
License: Apache-2.0
Author: Xanadu
Author-email: filippo@xanadu.ai
Requires-Python: >=3.9,<3.12
Classifier: Development Status :: 4 - Beta
Classifier: Environment :: Console
Classifier: Intended Audience :: Science/Research
Classifier: License :: OSI Approved :: Apache Software License
Classifier: Natural Language :: English
Classifier: Operating System :: MacOS :: MacOS X
Classifier: Operating System :: Microsoft :: Windows
Classifier: Operating System :: POSIX
Classifier: Operating System :: POSIX :: Linux
Classifier: Programming Language :: Python
Classifier: Programming Language :: Python :: 3
Classifier: Programming Language :: Python :: 3.9
Classifier: Programming Language :: Python :: 3.10
Classifier: Programming Language :: Python :: 3.11
Classifier: Programming Language :: Python :: 3 :: Only
Classifier: Topic :: Scientific/Engineering :: Physics
Provides-Extra: ray
Requires-Dist: grpcio (==1.60.0)
Requires-Dist: ipython (>=8.18.1)
Requires-Dist: julia (==0.6.1)
Requires-Dist: matplotlib (>=3.5.0,<4.0.0)
Requires-Dist: networkx (>=3.1,<4.0)
Requires-Dist: numba (>=0.59,<0.60)
Requires-Dist: numpy (>=1.23.5,<2.0.0)
Requires-Dist: ray[tune] (>=2.5.0,<3.0.0) ; extra == "ray"
Requires-Dist: rich (>=10.15.1,<11.0.0)
Requires-Dist: scikit-optimize (>=0.9.0,<0.10.0) ; extra == "ray"
Requires-Dist: scipy (>=1.8.0,<2.0.0)
Requires-Dist: tensorflow (>=2.15.0,<3.0.0)
Requires-Dist: tensorflow-cpu-aws (>=2.15.0,<3.0.0) ; (platform_machine == "arm64" or platform_machine == "aarch64") and sys_platform == "linux"
Requires-Dist: tensorflow-intel (>=2.15.0,<3.0.0) ; sys_platform == "win32"
Requires-Dist: tensorflow-io-gcs-filesystem (<0.32.0) ; platform_system == "Windows"
Requires-Dist: tensorflow-io-gcs-filesystem (>=0.23.1) ; platform_machine != "arm64" or platform_system != "Darwin"
Requires-Dist: tensorflow-macos (==2.15.0) ; platform_machine == "arm64" and sys_platform == "darwin"
Requires-Dist: tensorflow-probability (>=0.22.0,<0.23.0)
Requires-Dist: thewalrus (>=0.19.0,<0.20.0)
